[
  {
    "name": "@babel/parser",
    "version": "7.21.3",
    "url": "https://www.npmjs.com/package/@babel/parser",
    "license": "MIT",
    "licenseUrl": "http://opensource.org/licenses/mit-license.php"
  },
  {
    "name": "@fortawesome/fontawesome-free",
    "version": "6.4.0",
    "url": "https://www.npmjs.com/package/@fortawesome/fontawesome-free",
    "license": "OFL-1.1-no-RFN",
    "licenseUrl": "http://scripts.sil.org/cms/scripts/page.php?item_id=OFL_web"
  },
  {
    "name": "@popperjs/core",
    "version": "2.11.7",
    "url": "https://www.npmjs.com/package/@popperjs/core",
    "license": "MIT",
    "licenseUrl": "http://opensource.org/licenses/mit-license.php"
  },
  {
    "name": "@vue/compiler-sfc",
    "version": "2.7.14",
    "url": "https://www.npmjs.com/package/@vue/compiler-sfc",
    "license": "MIT",
    "licenseUrl": "http://opensource.org/licenses/mit-license.php"
  },
  {
    "name": "bootstrap",
    "version": "5.2.3",
    "url": "https://www.npmjs.com/package/bootstrap",
    "license": "MIT",
    "licenseUrl": "http://opensource.org/licenses/mit-license.php"
  },
  {
    "name": "csstype",
    "version": "3.1.1",
    "url": "https://www.npmjs.com/package/csstype",
    "license": "MIT",
    "licenseUrl": "http://opensource.org/licenses/mit-license.php"
  },
  {
    "name": "nanoid",
    "version": "3.3.6",
    "url": "https://www.npmjs.com/package/nanoid",
    "license": "MIT",
    "licenseUrl": "http://opensource.org/licenses/mit-license.php"
  },
  {
    "name": "picocolors",
    "version": "1.0.0",
    "url": "https://www.npmjs.com/package/picocolors",
    "license": "ISC",
    "licenseUrl": "https://www.isc.org/licenses/"
  },
  {
    "name": "postcss",
    "version": "8.4.21",
    "url": "https://www.npmjs.com/package/postcss",
    "license": "MIT",
    "licenseUrl": "http://opensource.org/licenses/mit-license.php"
  },
  {
    "name": "source-map-js",
    "version": "1.0.2",
    "url": "https://www.npmjs.com/package/source-map-js",
    "license": "BSD-3-Clause",
    "licenseUrl": "http://www.opensource.org/licenses/BSD-3-Clause"
  },
  {
    "name": "source-map",
    "version": "0.6.1",
    "url": "https://www.npmjs.com/package/source-map",
    "license": "BSD-3-Clause",
    "licenseUrl": "http://www.opensource.org/licenses/BSD-3-Clause"
  },
  {
    "name": "vue",
    "version": "2.7.14",
    "url": "https://www.npmjs.com/package/vue",
    "license": "MIT",
    "licenseUrl": "http://opensource.org/licenses/mit-license.php"
  }
]