{
  "total": 0,
  "tools inspection": {
    "Code Inspection": 0
  },
  "linter": "QDPY",
  "attributes": {
    "vcs": {
      "sarifIdea": {
        "repositoryUri": "https://github.com/LizardByte/Sunshine.git",
        "revisionId": "acc3962f3d0e36fe5e9b29c3bd02b717a19fac20",
        "branch": "build(docker)-free-additional-space-on-runners"
      }
    },
    "deviceId": "200820300000000-f3f0-513a-9341-b6fa25d1e779",
    "jobUrl": "https://github.com/LizardByte/Sunshine/actions/runs/5565306423",
    "repoUrl": "https://github.com/LizardByte/Sunshine.git"
  }
}