{
  "total": 0,
  "tools inspection": {
    "Code Inspection": 0
  },
  "linter": "QDPY",
  "attributes": {
    "vcs": {
      "sarifIdea": {
        "repositoryUri": "https://github.com/LizardByte/Sunshine.git",
        "revisionId": "39c129ba753987dfd908c628645d862b492d8023",
        "branch": "nightly"
      }
    },
    "deviceId": "200820300000000-f3f0-513a-9341-b6fa25d1e779",
    "jobUrl": "https://github.com/LizardByte/Sunshine/actions/runs/5767205776",
    "repoUrl": "https://github.com/LizardByte/Sunshine.git"
  }
}